bunyan_formatter/__init__.py
bunyan_formatter/logger.py
bunyan_formatter/py.typed
bunyan_formatter-1.0.0.dist-info/METADATA
bunyan_formatter-1.0.0.dist-info/WHEEL
bunyan_formatter-1.0.0.dist-info/licenses/LICENSE
bunyan_formatter-1.0.0.dist-info/RECORD
