Metadata-Version: 2.3
Name: bunyan-formatter
Version: 1.0.0
Summary: Bunyan Formatter for Python
Author-email: Kristofers Solo <dev@kristofers.xyz>
License-File: LICENSE
Requires-Python: >=3.9
